LICENSE.txt
MANIFEST.in
README.md
setup.cfg
setup.py
elasticsearch_dbapi_mod_amey.egg-info/PKG-INFO
elasticsearch_dbapi_mod_amey.egg-info/SOURCES.txt
elasticsearch_dbapi_mod_amey.egg-info/dependency_links.txt
elasticsearch_dbapi_mod_amey.egg-info/entry_points.txt
elasticsearch_dbapi_mod_amey.egg-info/not-zip-safe
elasticsearch_dbapi_mod_amey.egg-info/requires.txt
elasticsearch_dbapi_mod_amey.egg-info/top_level.txt
es/__init__.py
es/baseapi.py
es/basesqlalchemy.py
es/const.py
es/exceptions.py
es/__pycache__/__init__.cpython-38.pyc
es/__pycache__/baseapi.cpython-38.pyc
es/__pycache__/const.cpython-38.pyc
es/__pycache__/exceptions.cpython-38.pyc
es/elastic/__init__.py
es/elastic/api.py
es/elastic/sqlalchemy.py
es/elastic/__pycache__/__init__.cpython-38.pyc
es/elastic/__pycache__/api.cpython-38.pyc
es/opendistro/__init__.py
es/opendistro/api.py
es/opendistro/sqlalchemy.py
es/tests/__init__.py
es/tests/test_0_fixtures.py
es/tests/test_dbapi.py
es/tests/test_sqlalchemy.py
es/tests/fixtures/__init__.py
es/tests/fixtures/data1.json
es/tests/fixtures/data1_mappings.json
es/tests/fixtures/fixtures.py
es/tests/fixtures/flights.json